nex_agent/__init__.py
nex_agent/_version.py
nex_agent/cli.py
nex_agent/database.py
nex_agent/framework.py
nex_agent/mcp_client.py
nex_agent/openapi_server.py
nex_agent/plugin_manager.py
nex_agent/prompts.py
nex_agent/webserver.py
nex_agent/static/android-chrome-192x192.png
nex_agent/static/android-chrome-512x512.png
nex_agent/static/app.js
nex_agent/static/apple-touch-icon.png
nex_agent/static/favicon-16x16.png
nex_agent/static/favicon-32x32.png
nex_agent/static/favicon.ico
nex_agent/static/index.html
nex_agent/static/site.webmanifest
nex_agent/static/style.css
nex_agent-0.5.2.dist-info/licenses/LICENSE
nex_agent-0.5.2.dist-info/METADATA
nex_agent-0.5.2.dist-info/WHEEL
nex_agent-0.5.2.dist-info/entry_points.txt
nex_agent-0.5.2.dist-info/top_level.txt
nex_agent-0.5.2.dist-info/RECORD
