Metadata-Version: 2.4
Name: nex-agent
Version: 0.5.2
Summary: NexAgent - AI 对话框架，支持多服务商、多模型切换、深度思考、工具调用、流式输出、多会话管理
Author: 3w4e
License: MIT
Project-URL: Homepage, https://gitee.com/candy_xt/NexAgent
Project-URL: Repository, https://gitee.com/candy_xt/NexAgent
Keywords: ai,chatbot,openai,llm,framework,nex,multi-session,deep-thinking
Classifier: Development Status :: 3 - Alpha
Classifier: Intended Audience :: Developers
Classifier: License :: OSI Approved :: MIT License
Classifier: Programming Language :: Python :: 3
Classifier: Programming Language :: Python :: 3.9
Classifier: Programming Language :: Python :: 3.10
Classifier: Programming Language :: Python :: 3.11
Classifier: Programming Language :: Python :: 3.12
Classifier: Topic :: Scientific/Engineering :: Artificial Intelligence
Requires-Python: >=3.9
License-File: LICENSE
Requires-Dist: openai>=1.0.0
Requires-Dist: requests>=2.31.0
Requires-Dist: click>=8.0.0
Requires-Dist: fastapi>=0.100.0
Requires-Dist: uvicorn>=0.23.0
Requires-Dist: pydantic>=2.0.0
Requires-Dist: python-multipart>=0.0.6
Dynamic: license-file
